[
  {
    "_id": "54b9a1c0d7c36f2cafc74f8f",
    "index": 0,
    "guid": "4392849e-04f5-43d7-a6bd-671f50403de9",
    "isActive": true,
    "balance": "$2,142.09",
    "picture": "http://placehold.it/32x32",
    "age": 30,
    "eyeColor": "green",
    "name": "Tabatha Rosales",
    "gender": "female",
    "company": "FROLIX",
    "email": "tabatharosales@frolix.com",
    "phone": "+1 (813) 501-3811",
    "address": "593 Grant Avenue, Croom, Colorado, 7234",
    "about": "Amet ea officia magna officia eu in culpa esse elit proident. Pariatur exercitation sint velit incididunt mollit. Fugiat ullamco labore pariatur adipisicing laborum veniam laborum minim sit. Amet amet nisi velit aute dolore duis. Excepteur ullamco reprehenderit laborum culpa nulla cupidatat id incididunt.\r\n",
    "registered": "2014-08-18T16:17:28 +05:00",
    "latitude": -51.036731,
    "longitude": 22.803701,
    "tags": [
      "velit",
      "Lorem",
      "amet",
      "ex",
      "adipisicing",
      "pariatur",
      "voluptate"
    ],
    "friends": [
      {
        "id": 0,
        "name": "Catalina Hudson"
      },
      {
        "id": 1,
        "name": "Tamika Rivas"
      },
      {
        "id": 2,
        "name": "Sparks Hayes"
      }
    ],
    "greeting": "Hello, Tabatha Rosales! You have 6 unread messages.",
    "favoriteFruit": "strawberry"
  },
  {
    "_id": "54b9a1c02131c680c5a7e361",
    "index": 1,
    "guid": "0c2a1b78-1c57-48b7-b3e4-914af0644759",
    "isActive": true,
    "balance": "$1,070.80",
    "picture": "http://placehold.it/32x32",
    "age": 25,
    "eyeColor": "blue",
    "name": "Leila Valentine",
    "gender": "female",
    "company": "DECRATEX",
    "email": "leilavalentine@decratex.com",
    "phone": "+1 (937) 447-2438",
    "address": "182 Rutland Road, Caspar, Nevada, 6036",
    "about": "Officia id aliqua duis esse commodo duis exercitation et. Non exercitation sunt exercitation est deserunt eu. Ipsum mollit aliquip culpa non ex duis ad pariatur sunt enim ad amet laboris magna. Voluptate veniam in fugiat aliqua minim officia proident ea deserunt dolore quis consectetur esse eu.\r\n",
    "registered": "2014-07-18T10:51:04 +05:00",
    "latitude": 1.159074,
    "longitude": -68.77021,
    "tags": [
      "officia",
      "magna",
      "nulla",
      "esse",
      "quis",
      "ea",
      "eu"
    ],
    "friends": [
      {
        "id": 0,
        "name": "Priscilla Alvarez"
      },
      {
        "id": 1,
        "name": "Duran Ward"
      },
      {
        "id": 2,
        "name": "Celeste Livingston"
      }
    ],
    "greeting": "Hello, Leila Valentine! You have 3 unread messages.",
    "favoriteFruit": "strawberry"
  },
  {
    "_id": "54b9a1c01cf11393c766f194",
    "index": 2,
    "guid": "c85c32e6-fcef-4b0d-9759-e9f72b2788f1",
    "isActive": false,
    "balance": "$3,017.87",
    "picture": "http://placehold.it/32x32",
    "age": 32,
    "eyeColor": "brown",
    "name": "Kenya Phelps",
    "gender": "female",
    "company": "BRAINQUIL",
    "email": "kenyaphelps@brainquil.com",
    "phone": "+1 (823) 455-2123",
    "address": "322 Veterans Avenue, Woodruff, Indiana, 508",
    "about": "Ea nulla nostrud ipsum aute pariatur. Ex sunt incididunt anim occaecat cupidatat eiusmod culpa proident. Mollit aliquip non sunt tempor voluptate dolor duis reprehenderit. Dolor laboris quis cillum sunt dolor voluptate ea labore aute cillum nisi irure. Nostrud commodo ad ea eu ut incididunt reprehenderit et fugiat eu.\r\n",
    "registered": "2014-03-27T13:57:04 +05:00",
    "latitude": -46.823373,
    "longitude": -117.503871,
    "tags": [
      "dolor",
      "exercitation",
      "qui",
      "exercitation",
      "exercitation",
      "incididunt",
      "nisi"
    ],
    "friends": [
      {
        "id": 0,
        "name": "Whitley Palmer"
      },
      {
        "id": 1,
        "name": "Haley Chang"
      },
      {
        "id": 2,
        "name": "Mamie Harris"
      }
    ],
    "greeting": "Hello, Kenya Phelps! You have 2 unread messages.",
    "favoriteFruit": "banana"
  },
  {
    "_id": "54b9a1c078c03fdf1554c521",
    "index": 3,
    "guid": "37acfbe8-6979-4c10-8aab-be6ef8e38ec8",
    "isActive": false,
    "balance": "$1,562.04",
    "picture": "http://placehold.it/32x32",
    "age": 23,
    "eyeColor": "brown",
    "name": "Madden Donaldson",
    "gender": "male",
    "company": "APPLICA",
    "email": "maddendonaldson@applica.com",
    "phone": "+1 (914) 502-2225",
    "address": "495 Blake Avenue, Mahtowa, Vermont, 2146",
    "about": "Deserunt irure qui consectetur velit in adipisicing id enim ullamco exercitation duis. Anim tempor dolore aute esse laborum in. Laboris esse duis amet reprehenderit. Ea esse deserunt pariatur labore amet. Velit velit dolor est ipsum ipsum cillum est in.\r\n",
    "registered": "2014-04-26T10:20:57 +05:00",
    "latitude": 65.222716,
    "longitude": 12.852452,
    "tags": [
      "tempor",
      "aliquip",
      "incididunt",
      "nisi",
      "minim",
      "consectetur",
      "anim"
    ],
    "friends": [
      {
        "id": 0,
        "name": "Daniel Chavez"
      },
      {
        "id": 1,
        "name": "Barton Alston"
      },
      {
        "id": 2,
        "name": "Curtis Castaneda"
      }
    ],
    "greeting": "Hello, Madden Donaldson! You have 6 unread messages.",
    "favoriteFruit": "banana"
  },
  {
    "_id": "54b9a1c0987777618db0e2f7",
    "index": 4,
    "guid": "49e5d2b6-6d4e-4eb8-a6fb-ac731eee2a32",
    "isActive": true,
    "balance": "$1,946.65",
    "picture": "http://placehold.it/32x32",
    "age": 40,
    "eyeColor": "blue",
    "name": "Love Hinton",
    "gender": "male",
    "company": "XYQAG",
    "email": "lovehinton@xyqag.com",
    "phone": "+1 (933) 430-2489",
    "address": "984 Fleet Walk, Craig, Puerto Rico, 5407",
    "about": "Irure veniam officia qui laborum. Qui officia reprehenderit eiusmod voluptate culpa dolor tempor veniam ut. Mollit cillum cupidatat reprehenderit in esse labore id magna consectetur cillum velit ex. Ea exercitation officia quis excepteur deserunt tempor magna magna non. Reprehenderit enim labore ad nulla esse exercitation duis irure nulla. Veniam non excepteur ut elit cillum excepteur anim amet nisi qui sit mollit proident. Mollit nisi officia adipisicing officia dolor adipisicing laboris ex velit.\r\n",
    "registered": "2014-10-02T23:26:01 +05:00",
    "latitude": -30.888185,
    "longitude": 97.009859,
    "tags": [
      "Lorem",
      "sit",
      "enim",
      "pariatur",
      "nostrud",
      "nisi",
      "id"
    ],
    "friends": [
      {
        "id": 0,
        "name": "George Vaughn"
      },
      {
        "id": 1,
        "name": "Sophia Larsen"
      },
      {
        "id": 2,
        "name": "Samantha Norman"
      }
    ],
    "greeting": "Hello, Love Hinton! You have 2 unread messages.",
    "favoriteFruit": "apple"
  },
  {
    "_id": "54b9a1c06987acb322c65bd0",
    "index": 5,
    "guid": "b3508a47-7b0c-4a1e-be02-2bd8c19b0b93",
    "isActive": false,
    "balance": "$3,050.01",
    "picture": "http://placehold.it/32x32",
    "age": 32,
    "eyeColor": "blue",
    "name": "Cameron Farmer",
    "gender": "male",
    "company": "QNEKT",
    "email": "cameronfarmer@qnekt.com",
    "phone": "+1 (867) 421-2049",
    "address": "751 Clifton Place, Innsbrook, Washington, 1776",
    "about": "Sit nisi in reprehenderit tempor cillum adipisicing velit eu dolor dolore excepteur voluptate. Magna consequat mollit excepteur tempor consectetur dolor Lorem consequat commodo occaecat magna consectetur. Do consectetur qui commodo commodo deserunt ea voluptate adipisicing Lorem magna eu voluptate. Velit mollit cupidatat labore anim ea labore eu non ipsum adipisicing ad ullamco ut culpa. Tempor mollit consequat reprehenderit Lorem excepteur minim.\r\n",
    "registered": "2014-11-20T04:54:12 +06:00",
    "latitude": 38.292081,
    "longitude": 115.20793,
    "tags": [
      "culpa",
      "non",
      "ad",
      "do",
      "voluptate",
      "ea",
      "aute"
    ],
    "friends": [
      {
        "id": 0,
        "name": "Cherry Frye"
      },
      {
        "id": 1,
        "name": "Marks Luna"
      },
      {
        "id": 2,
        "name": "Jackson Long"
      }
    ],
    "greeting": "Hello, Cameron Farmer! You have 4 unread messages.",
    "favoriteFruit": "strawberry"
  },
  {
    "_id": "54b9a1c125ec0a6cc03b9ba5",
    "index": 6,
    "guid": "ca495ca6-0349-48e1-ac00-c9a84725d008",
    "isActive": false,
    "balance": "$3,156.32",
    "picture": "http://placehold.it/32x32",
    "age": 40,
    "eyeColor": "blue",
    "name": "Nanette Evans",
    "gender": "female",
    "company": "TERRAGO",
    "email": "nanetteevans@terrago.com",
    "phone": "+1 (843) 454-3671",
    "address": "964 Story Street, Alleghenyville, Delaware, 1547",
    "about": "Et ullamco irure veniam id occaecat reprehenderit do veniam amet veniam magna. Sit laboris commodo ullamco deserunt nisi et sunt incididunt ullamco. Quis Lorem ex incididunt mollit adipisicing. Eu proident proident quis occaecat enim ullamco ullamco cupidatat esse sunt culpa aliquip id sunt. Consectetur nulla dolor nulla laborum ipsum. Nostrud cupidatat minim ullamco proident reprehenderit ea dolore. Aliquip non sit est dolore deserunt cillum excepteur culpa excepteur qui cupidatat mollit.\r\n",
    "registered": "2014-11-02T01:26:44 +05:00",
    "latitude": 89.676219,
    "longitude": -64.027945,
    "tags": [
      "qui",
      "excepteur",
      "consequat",
      "non",
      "proident",
      "elit",
      "quis"
    ],
    "friends": [
      {
        "id": 0,
        "name": "Whitfield Decker"
      },
      {
        "id": 1,
        "name": "Eileen Patterson"
      },
      {
        "id": 2,
        "name": "Casey Suarez"
      }
    ],
    "greeting": "Hello, Nanette Evans! You have 3 unread messages.",
    "favoriteFruit": "strawberry"
  }
]